game_module/__init__.py
game_module/cli.py
xx_game_module-1.0.1.dist-info/METADATA
xx_game_module-1.0.1.dist-info/WHEEL
xx_game_module-1.0.1.dist-info/entry_points.txt
xx_game_module-1.0.1.dist-info/top_level.txt
xx_game_module-1.0.1.dist-info/RECORD
